script/cli.py
test_topsis-1.0.0.dist-info/LICENSE
test_topsis-1.0.0.dist-info/METADATA
test_topsis-1.0.0.dist-info/WHEEL
test_topsis-1.0.0.dist-info/entry_points.txt
test_topsis-1.0.0.dist-info/top_level.txt
test_topsis-1.0.0.dist-info/RECORD
