Metadata-Version: 2.1
Name: test-topsis
Version: 1.0.0
Summary: A Python package to implement Topsis
Home-page: UNKNOWN
Author: Rajat Verma
Author-email: rajatv864@gmail.com
License: MIT
Platform: UNKNOWN
Classifier: License :: OSI Approved :: MIT License
Classifier: Programming Language :: Python :: 3
Classifier: Programming Language :: Python :: 3.7
Requires-Dist: numpy
Requires-Dist: pandas
